pycaber-0.1.3.dist-info/METADATA
pycaber-0.1.3.dist-info/WHEEL
pycaber.pyi
pycaber/__init__.py
pycaber/__init__.pyi
pycaber/py.typed
pycaber/pycaber.abi3.so
pycaber-0.1.3.dist-info/RECORD
