Metadata-Version: 2.4
Name: pycaber
Version: 0.1.3
Classifier: Programming Language :: Rust
Classifier: Programming Language :: Python :: Implementation :: CPython
Classifier: Programming Language :: Python :: Implementation :: PyPy
Classifier: Development Status :: 4 - Beta
Summary: Caber DREAM: Deterministic Attribution and Control of AI Data Use
Author: Caber Systems, Inc. <dev@caber.com>
Author-email: "Caber Systems, Inc." <dev@caber.com>
Requires-Python: >=3.9
Project-URL: Homepage, https://caber.com
